etherbase_predeployed/__init__.py
etherbase_predeployed/address.py
etherbase_predeployed/etherbase_generator.py
etherbase_predeployed/etherbase_upgradeable_generator.py
etherbase_predeployed/py.typed
etherbase_predeployed/artifacts/.keep
etherbase_predeployed/artifacts/Etherbase.json
etherbase_predeployed/artifacts/EtherbaseUpgradeable.json
etherbase_predeployed-1.0.0.dist-info/METADATA
etherbase_predeployed-1.0.0.dist-info/WHEEL
etherbase_predeployed-1.0.0.dist-info/top_level.txt
etherbase_predeployed-1.0.0.dist-info/RECORD
